<?xml version="1.0" encoding="utf-8"?>
<resumes>
  <resume>
    <AppID>1</AppID>
    <ContactInfo>
      <FirstName>Timothy</FirstName>
      <LastName>Lin</LastName>
      <MiddleInitial />
      <Prefix>Mr.</Prefix>
      <Suffix>Jr.</Suffix>
      <Email>t@g.com</Email>
      <PhoneNumber>1112223345</PhoneNumber>
    </ContactInfo>
    <Address>
      <AddressLine1>100 S Main St.</AddressLine1>
      <AddressLine2>Apt 145</AddressLine2>
      <City>Akron</City>
      <State>Ohio</State>
      <Zipcode>44311</Zipcode>
    </Address>
    <Position>
      <PositionID>0</PositionID>
      <PositionName>Janitor</PositionName>
      <PostedDate>0001-01-01T00:00:00</PostedDate>
      <ClosingDate>0001-01-01T00:00:00</ClosingDate>
      <Description></Description>
    </Position>
    <Experience>
      <Company>Software Guild</Company>
      <Title>Victor</Title>
      <StartDate>2015-11-03T00:00:00</StartDate>
      <EndDate>2015-11-06T00:00:00</EndDate>
      <Location>
        <AddressLine1 />
        <AddressLine2 />
        <City>Akron</City>
        <State>Ohio</State>
        <Zipcode />
      </Location>
      <Description />
      <SupervisorName>Eric Wise</SupervisorName>
      <SupervisorPhone>1234567890</SupervisorPhone>
      <SupervisorEmail>t@g.com</SupervisorEmail>
    </Experience>
    <Education>
      <Degree>BS</Degree>
      <Institution>Wheaton College</Institution>
      <Location>
        <AddressLine1 />
        <AddressLine2 />
        <City>Wheaton</City>
        <State>Illinois</State>
        <Zipcode />
      </Location>
      <StartDate>2015-11-16T00:00:00</StartDate>
      <GraduationDate>2015-11-20T00:00:00</GraduationDate>
      <GPA>4</GPA>
      <Concentration>Chemistry</Concentration>
    </Education>
    <DesiredSalary>1000000</DesiredSalary>
    <AppDate>2015-11-27T00:00:00</AppDate>
  </resume>
  <resume>
    <AppID>2</AppID>
    <ContactInfo>
      <FirstName>Timothy</FirstName>
      <LastName>Lin</LastName>
      <MiddleInitial />
      <Prefix>Mr.</Prefix>
      <Suffix>Jr.</Suffix>
      <Email>t@g.com</Email>
      <PhoneNumber>1112223345</PhoneNumber>
    </ContactInfo>
    <Address>
      <AddressLine1>100 S Main St.</AddressLine1>
      <AddressLine2>Apt 145</AddressLine2>
      <City>Akron</City>
      <State>Ohio</State>
      <Zipcode>44311</Zipcode>
    </Address>
    <Position>
      <PositionID>0</PositionID>
      <PositionName>Janitor</PositionName>
      <PostedDate>0001-01-01T00:00:00</PostedDate>
      <ClosingDate>0001-01-01T00:00:00</ClosingDate>
      <Description></Description>
    </Position>
    <Experience>
      <Company>Software Guild</Company>
      <Title>Victor</Title>
      <StartDate>2015-11-03T00:00:00</StartDate>
      <EndDate>2015-11-06T00:00:00</EndDate>
      <Location>
        <AddressLine1 />
        <AddressLine2 />
        <City>Akron</City>
        <State>Ohio</State>
        <Zipcode />
      </Location>
      <Description />
      <SupervisorName>Eric Wise</SupervisorName>
      <SupervisorPhone>1234567890</SupervisorPhone>
      <SupervisorEmail>t@g.com</SupervisorEmail>
    </Experience>
    <Education>
      <Degree>BS</Degree>
      <Institution>Wheaton College</Institution>
      <Location>
        <AddressLine1 />
        <AddressLine2 />
        <City>Wheaton</City>
        <State>Illinois</State>
        <Zipcode />
      </Location>
      <StartDate>2015-11-16T00:00:00</StartDate>
      <GraduationDate>2015-11-20T00:00:00</GraduationDate>
      <GPA>4</GPA>
      <Concentration>Chemistry</Concentration>
    </Education>
    <DesiredSalary>1000000</DesiredSalary>
    <AppDate>2015-11-27T00:00:00</AppDate>
  </resume>
  <resume>
    <AppID>3</AppID>
    <ContactInfo>
      <FirstName>Homer</FirstName>
      <LastName>Simpson</LastName>
      <MiddleInitial />
      <Prefix>Mr.</Prefix>
      <Suffix>Jr.</Suffix>
      <Email>h@s.com</Email>
      <PhoneNumber>1234567890</PhoneNumber>
    </ContactInfo>
    <Address>
      <AddressLine1>100 N Main St</AddressLine1>
      <AddressLine2>Apt 5412</AddressLine2>
      <City>Akron</City>
      <State>Ohio</State>
      <Zipcode>60187</Zipcode>
    </Address>
    <Position>
      <PositionID>0</PositionID>
      <PositionName>Instructor</PositionName>
      <Description />
      <PostedDate>0001-01-01T00:00:00</PostedDate>
      <ClosingDate>0001-01-01T00:00:00</ClosingDate>
    </Position>
    <Experience>
      <Company>Foo</Company>
      <Title>CEO</Title>
      <StartDate>2015-11-11T00:00:00</StartDate>
      <EndDate>2015-11-20T00:00:00</EndDate>
      <Location>
        <AddressLine1 />
        <AddressLine2 />
        <City>Springfiled</City>
        <State>Illinois</State>
        <Zipcode />
      </Location>
      <Description />
      <SupervisorName>Eric Wise</SupervisorName>
      <SupervisorPhone>1234567890</SupervisorPhone>
      <SupervisorEmail>e@g.com</SupervisorEmail>
    </Experience>
    <Education>
      <Degree>Associates</Degree>
      <Institution>Stark College</Institution>
      <Location>
        <AddressLine1 />
        <AddressLine2 />
        <City>Canton</City>
        <State>Ohio</State>
        <Zipcode />
      </Location>
      <StartDate>2015-11-12T00:00:00</StartDate>
      <GraduationDate>2015-11-20T00:00:00</GraduationDate>
      <GPA>56</GPA>
      <Concentration>Comm</Concentration>
    </Education>
    <DesiredSalary>10000000</DesiredSalary>
    <AppDate>2015-11-26T00:00:00</AppDate>
  </resume>
  <resume>
    <AppID>4</AppID>
    <ContactInfo>
      <FirstName>d</FirstName>
      <LastName>b</LastName>
      <MiddleInitial />
      <Prefix />
      <Suffix />
      <Email />
      <PhoneNumber />
    </ContactInfo>
    <Address>
      <AddressLine1 />
      <AddressLine2 />
      <City />
      <State>Alaska</State>
      <Zipcode />
    </Address>
    <Position>
      <PositionID>0</PositionID>
      <PositionName>Manager</PositionName>
      <Description />
      <PostedDate>0001-01-01T00:00:00</PostedDate>
      <ClosingDate />
    </Position>
    <Experience>
      <Company />
      <Title />
      <StartDate>2015-11-04T00:00:00</StartDate>
      <EndDate>2015-11-13T00:00:00</EndDate>
      <Location>
        <AddressLine1 />
        <AddressLine2 />
        <City />
        <State>Alaska</State>
        <Zipcode />
      </Location>
      <Description />
      <SupervisorName />
      <SupervisorPhone />
      <SupervisorEmail />
    </Experience>
    <Education>
      <Degree>Unknown</Degree>
      <Institution />
      <Location>
        <AddressLine1 />
        <AddressLine2 />
        <City />
        <State>Alaska</State>
        <Zipcode />
      </Location>
      <StartDate>2015-11-25T00:00:00</StartDate>
      <GraduationDate>2015-11-27T00:00:00</GraduationDate>
      <GPA>4</GPA>
      <Concentration />
    </Education>
    <DesiredSalary>0</DesiredSalary>
    <AppDate>2015-11-28T00:00:00</AppDate>
  </resume>
  <resume>
    <AppID>5</AppID>
    <ContactInfo>
      <FirstName>adf</FirstName>
      <LastName>ea</LastName>
      <MiddleInitial />
      <Prefix>d</Prefix>
      <Suffix>ab</Suffix>
      <Email>g@c.com</Email>
      <PhoneNumber>8888888888</PhoneNumber>
    </ContactInfo>
    <Address>
      <AddressLine1>123 s main st.</AddressLine1>
      <AddressLine2>apt. 234</AddressLine2>
      <City>w</City>
      <State>Idaho</State>
      <Zipcode>18976</Zipcode>
    </Address>
    <Position>
      <PositionID>0</PositionID>
      <PositionName>New Victor</PositionName>
      <Description />
      <PostedDate>0001-01-01T00:00:00</PostedDate>
      <ClosingDate />
    </Position>
    <Experience>
      <Company>tlasdf</Company>
      <Title>aehad</Title>
      <StartDate>2015-11-24T00:00:00</StartDate>
      <EndDate>2015-11-28T00:00:00</EndDate>
      <Location>
        <AddressLine1 />
        <AddressLine2 />
        <City>dafh</City>
        <State>Arkansas</State>
        <Zipcode />
      </Location>
      <Description />
      <SupervisorName>asdf</SupervisorName>
      <SupervisorPhone>0000000000</SupervisorPhone>
      <SupervisorEmail>34@g.com</SupervisorEmail>
    </Experience>
    <Education>
      <Degree>GED</Degree>
      <Institution>ae</Institution>
      <Location>
        <AddressLine1 />
        <AddressLine2 />
        <City>age</City>
        <State>Colorado</State>
        <Zipcode />
      </Location>
      <StartDate>2015-11-25T00:00:00</StartDate>
      <GraduationDate>2015-11-28T00:00:00</GraduationDate>
      <GPA>3.5</GPA>
      <Concentration>asdf</Concentration>
    </Education>
    <DesiredSalary>1111111</DesiredSalary>
    <AppDate>2015-11-27T00:00:00</AppDate>
  </resume>
  <resume>
    <AppID>6</AppID>
    <ContactInfo>
      <FirstName>Jim</FirstName>
      <LastName>Johnson</LastName>
      <MiddleInitial />
      <Prefix>Mr.</Prefix>
      <Suffix>Jr.</Suffix>
      <Email>jj@gmail.com</Email>
      <PhoneNumber>8881112345</PhoneNumber>
    </ContactInfo>
    <Address>
      <AddressLine1>2123 S. Main St.</AddressLine1>
      <AddressLine2>Apt 534</AddressLine2>
      <City>Akron</City>
      <State>Ohio</State>
      <Zipcode>44311</Zipcode>
    </Address>
    <Position>
      <PositionID>0</PositionID>
      <PositionName>Janitor</PositionName>
      <Description />
      <PostedDate>0001-01-01T00:00:00</PostedDate>
      <ClosingDate />
    </Position>
    <Experience>
      <Company>Foo</Company>
      <Title>Yay</Title>
      <StartDate>2015-12-16T00:00:00</StartDate>
      <EndDate>2015-12-18T00:00:00</EndDate>
      <Location>
        <AddressLine1 />
        <AddressLine2 />
        <City>Little Rock</City>
        <State>Arkansas</State>
        <Zipcode />
      </Location>
      <Description />
      <SupervisorName>Name</SupervisorName>
      <SupervisorPhone>1234567890</SupervisorPhone>
      <SupervisorEmail>s@email.com</SupervisorEmail>
    </Experience>
    <Education>
      <Degree>BS</Degree>
      <Institution>Institution</Institution>
      <Location>
        <AddressLine1 />
        <AddressLine2 />
        <City>NYC</City>
        <State>New York</State>
        <Zipcode />
      </Location>
      <StartDate>2015-12-15T00:00:00</StartDate>
      <GraduationDate>2015-12-17T00:00:00</GraduationDate>
      <GPA>4.0</GPA>
      <Concentration>conc</Concentration>
    </Education>
    <DesiredSalary>100000</DesiredSalary>
    <AppDate>2015-12-30T00:00:00</AppDate>
  </resume>
  <resume>
    <AppID>0</AppID>
    <ContactInfo>
      <FirstName>Jim</FirstName>
      <LastName>Johnson</LastName>
      <MiddleInitial />
      <Prefix>Mr.</Prefix>
      <Suffix>Jr.</Suffix>
      <Email>jj@gmail.com</Email>
      <PhoneNumber>8881112345</PhoneNumber>
    </ContactInfo>
    <Address>
      <AddressLine1>2123 S. Main St.</AddressLine1>
      <AddressLine2>Apt 534</AddressLine2>
      <City>Akron</City>
      <State>Ohio</State>
      <Zipcode>44311</Zipcode>
    </Address>
    <Position>
      <PositionID>0</PositionID>
      <PositionName>Janitor</PositionName>
      <Description />
      <PostedDate>0001-01-01T00:00:00</PostedDate>
      <ClosingDate />
    </Position>
    <Experience>
      <Company>Foo</Company>
      <Title>Yay</Title>
      <StartDate>2015-12-16T00:00:00</StartDate>
      <EndDate>2015-12-18T00:00:00</EndDate>
      <Location>
        <AddressLine1 />
        <AddressLine2 />
        <City>Little Rock</City>
        <State>Arkansas</State>
        <Zipcode />
      </Location>
      <Description />
      <SupervisorName>Name</SupervisorName>
      <SupervisorPhone>1234567890</SupervisorPhone>
      <SupervisorEmail>s@email.com</SupervisorEmail>
    </Experience>
    <Education>
      <Degree>BS</Degree>
      <Institution>Institution</Institution>
      <Location>
        <AddressLine1 />
        <AddressLine2 />
        <City>NYC</City>
        <State>New York</State>
        <Zipcode />
      </Location>
      <StartDate>2015-12-15T00:00:00</StartDate>
      <GraduationDate>2015-12-17T00:00:00</GraduationDate>
      <GPA>4.0</GPA>
      <Concentration>conc</Concentration>
    </Education>
    <DesiredSalary>100000</DesiredSalary>
    <AppDate>2015-12-30T00:00:00</AppDate>
  </resume>
  <resume>
    <AppID>7</AppID>
    <ContactInfo>
      <FirstName>Joanna</FirstName>
      <LastName>Smith</LastName>
      <MiddleInitial />
      <Prefix>Ms.</Prefix>
      <Suffix>Sr.</Suffix>
      <Email>js@jsdate.com</Email>
      <PhoneNumber>1234567890</PhoneNumber>
    </ContactInfo>
    <Address>
      <AddressLine1>1234 Line 1</AddressLine1>
      <AddressLine2>Line 2</AddressLine2>
      <City>City</City>
      <State>Alabama</State>
      <Zipcode>11111</Zipcode>
    </Address>
    <Position>
      <PositionID>0</PositionID>
      <PositionName>New Victor</PositionName>
      <Description />
      <PostedDate>0001-01-01T00:00:00</PostedDate>
      <ClosingDate />
    </Position>
    <Experience>
      <Company>asdf</Company>
      <Title>title</Title>
      <StartDate>2015-12-15T00:00:00</StartDate>
      <EndDate>2015-12-25T00:00:00</EndDate>
      <Location>
        <AddressLine1 />
        <AddressLine2 />
        <City>city</City>
        <State>Arkansas</State>
        <Zipcode />
      </Location>
      <Description />
      <SupervisorName>name</SupervisorName>
      <SupervisorPhone>1234567890</SupervisorPhone>
      <SupervisorEmail>em@mail.com</SupervisorEmail>
    </Experience>
    <Education>
      <Degree>BS</Degree>
      <Institution>name</Institution>
      <Location>
        <AddressLine1 />
        <AddressLine2 />
        <City>city</City>
        <State>Colorado</State>
        <Zipcode />
      </Location>
      <StartDate>2015-12-07T00:00:00</StartDate>
      <GraduationDate>2015-12-22T00:00:00</GraduationDate>
      <GPA>4.0</GPA>
      <Concentration>conc</Concentration>
    </Education>
    <DesiredSalary>100000</DesiredSalary>
    <AppDate>2015-12-21T00:00:00</AppDate>
  </resume>
  <resume>
    <AppID>8</AppID>
    <ContactInfo>
      <FirstName>Jinping</FirstName>
      <LastName>Xi</LastName>
      <MiddleInitial />
      <Prefix>Dr.</Prefix>
      <Suffix>Sr.</Suffix>
      <Email>xi@china.com</Email>
      <PhoneNumber>3214567890</PhoneNumber>
    </ContactInfo>
    <Address>
      <AddressLine1>Line 1</AddressLine1>
      <AddressLine2>Line 2</AddressLine2>
      <City>Beijing</City>
      <State>California</State>
      <Zipcode>43105</Zipcode>
    </Address>
    <Position>
      <PositionID>0</PositionID>
      <PositionName>Manager</PositionName>
      <Description />
      <PostedDate>0001-01-01T00:00:00</PostedDate>
      <ClosingDate />
    </Position>
    <Experience>
      <Company>Chinese Government</Company>
      <Title>Zhuxi</Title>
      <StartDate>2015-12-14T00:00:00</StartDate>
      <EndDate>2015-12-16T00:00:00</EndDate>
      <Location>
        <AddressLine1 />
        <AddressLine2 />
        <City>Beijing</City>
        <State>California</State>
        <Zipcode />
      </Location>
      <Description />
      <SupervisorName>None</SupervisorName>
      <SupervisorPhone>5461327891</SupervisorPhone>
      <SupervisorEmail>e@email.com</SupervisorEmail>
    </Experience>
    <Education>
      <Degree>MS</Degree>
      <Institution>Peking University</Institution>
      <Location>
        <AddressLine1 />
        <AddressLine2 />
        <City>Beijing</City>
        <State>Connecticut</State>
        <Zipcode />
      </Location>
      <StartDate>2015-12-08T00:00:00</StartDate>
      <GraduationDate>2015-12-22T00:00:00</GraduationDate>
      <GPA>4.2</GPA>
      <Concentration>conc</Concentration>
    </Education>
    <DesiredSalary>10000000</DesiredSalary>
    <AppDate>2015-12-30T00:00:00</AppDate>
  </resume>
  <resume>
    <AppID>9</AppID>
    <ContactInfo>
      <FirstName>Dean</FirstName>
      <LastName>Choi</LastName>
      <MiddleInitial />
      <Prefix>Mr</Prefix>
      <Suffix />
      <Email>deanchoi@gmail.com</Email>
      <PhoneNumber>440-263-5132</PhoneNumber>
    </ContactInfo>
    <Address>
      <AddressLine1>8993 Crooked Creek Ln</AddressLine1>
      <AddressLine2 />
      <City>Broadview Heights</City>
      <State>Ohio</State>
      <Zipcode>44147</Zipcode>
    </Address>
    <Position>
      <PositionID>0</PositionID>
      <PositionName>New Victor</PositionName>
      <Description />
      <PostedDate>0001-01-01T00:00:00</PostedDate>
      <ClosingDate />
    </Position>
    <Experience>
      <Company>deanzel Entertainment Conglormerate</Company>
      <Title>DJ</Title>
      <StartDate>2014-01-01T00:00:00</StartDate>
      <EndDate>2015-08-31T00:00:00</EndDate>
      <Location>
        <AddressLine1 />
        <AddressLine2 />
        <City>Philadelphia</City>
        <State>Pennsylvania</State>
        <Zipcode />
      </Location>
      <Description />
      <SupervisorName>The "Real" Timothy Lin</SupervisorName>
      <SupervisorPhone>137-999-1337</SupervisorPhone>
      <SupervisorEmail>timOGlin@gmail.com</SupervisorEmail>
    </Experience>
    <Education>
      <Degree>BS</Degree>
      <Institution>Duke University</Institution>
      <Location>
        <AddressLine1 />
        <AddressLine2 />
        <City>Durham</City>
        <State>North Carolina</State>
        <Zipcode />
      </Location>
      <StartDate>2005-08-01T00:00:00</StartDate>
      <GraduationDate>2009-05-01T00:00:00</GraduationDate>
      <GPA>3.7</GPA>
      <Concentration>Biology &amp; Chemistry</Concentration>
    </Education>
    <DesiredSalary>1337</DesiredSalary>
    <AppDate>2015-12-04T00:00:00</AppDate>
  </resume>
</resumes>